{
    "version": "3.0.5",
    "description": "Simple, easy-to-use database manager",
    "homepage": "https://dataflare.app",
    "license": "Unknown",
    "architecture": {
        "64bit": {
            "url": "https://assets.dataflare.app/release/windows/x86_64/Dataflare-Setup-3.0.5.exe#/dl.7z",
            "hash": "31c36a4491305dc193cc8918b6402a0c3407f920d6f2e55a8552b031880c5e55"
        }
    },
    "pre_install": "Remove-Item \"$dir\\`$PLUGINSDIR\", \"$dir\\uninst*\" -Force -Recurse",
    "shortcuts": [
        [
            "dataflare.exe",
            "Dataflare"
        ]
    ],
    "checkver": {
        "url": "https://github.com/DataflareApp/dataflare/blob/main/CHANGELOG.md",
        "regex": "## v([0-9.]+)"
    },
    "autoupdate":{
        "architecture": {
            "64bit": {
                "url": "https://assets.dataflare.app/release/windows/x86_64/Dataflare-Setup-$version.exe#/dl.7z"
            }
        }
    }
}
