{
    "version": "1.16.0",
    "homepage": "https://tigervnc.org",
    "description": "TigerVNC is a platform-neutral implementation of VNC.",
    "license": "GPL-2.0-only",
    "architecture": {
        "64bit": {
            "url": "https://downloads.sourceforge.net/project/tigervnc/stable/1.16.0/tigervnc64-1.16.0.exe",
            "hash": "f2550b76bab97c487888e58449407bd9363dbb8fb4eb857fe26dfefbaf5b2ce8"
        }
    },
    "innosetup": true,
    "shortcuts": [
        [
            "vncviewer.exe",
            "TigerVNC Viewer"
        ]
    ],
    "checkver": {
        "github": "https://github.com/TigerVNC/tigervnc"
    },
    "autoupdate": {
        "architecture": {
            "64bit": {
                "url": "https://downloads.sourceforge.net/project/tigervnc/stable/$version/tigervnc64-$version.exe"
            }
        }
    },
    "notes": [
        "This package only contains TigerVNC Viewer (vncviewer) currently."
    ]
}
